{"note":"Don't delete this file! It's used internally to help with page regeneration.","name":"Slice","tagline":"Reading Center Interface for dynamic PDF report generation and quality checking","body":"### Slice \r\nA clinical research interface geared at collecting robust and consistent data by providing a strong framework for designing data dictionaries and collection forms. Slice also provides exports of the data and the data dictionaries created as well as providing a simple reporting interface. Using Rails 3.2+ and Ruby 1.9.3+.\r\n\r\n### Copyright ![http://i.creativecommons.org/l/by-nc-sa/3.0/80x15.png](http://creativecommons.org/licenses/by-nc-sa/3.0/)\r\n\r\nCopyright (c) 2012 Remo Mueller. See [LICENSE](https://github.com/remomueller/slice/blob/master/LICENSE) for further details.","google":""}